inno_control/__init__.py
inno_control/core.py
inno_control/exceptions.py
inno_control/mujoco.py
inno_control/devices/__init__.py
inno_control/devices/cart_pole.py
inno_control/devices/lab_device.py
inno_control/devices/port_scan.py
InnoControl-0.1.4.dist-info/METADATA
InnoControl-0.1.4.dist-info/WHEEL
InnoControl-0.1.4.dist-info/top_level.txt
InnoControl-0.1.4.dist-info/RECORD
