Metadata-Version: 2.1
Name: InnoControl
Version: 0.1.4
Summary: Lib for Innopolis Robotics Lab control platforms
Home-page: https://github.com/IU-Capstone-Project-2025/total_control
Author: Dungeon team
Author-email: e.shlomov@innopolis.university
License: UNKNOWN
Platform: UNKNOWN
Classifier: Programming Language :: Python :: 3
Classifier: License :: OSI Approved :: MIT License
Classifier: Operating System :: OS Independent
Requires-Python: >=3.6
Requires-Dist: control (>=0.9)
Requires-Dist: gymnasium (>=0.28)
Requires-Dist: matplotlib (>=3.7)
Requires-Dist: mujoco (>=3.3)
Requires-Dist: numpy (>=1.22)
Requires-Dist: pyserial (>=3.5)
Requires-Dist: scipy (>=1.10)
Requires-Dist: torch (>=2.0)
